odoo8_addon_mrp_operations_start_without_material-8.0.1.0.1.99.dev6-py2.7-nspkg.pth
odoo8_addon_mrp_operations_start_without_material-8.0.1.0.1.99.dev6.dist-info/DESCRIPTION.rst
odoo8_addon_mrp_operations_start_without_material-8.0.1.0.1.99.dev6.dist-info/METADATA
odoo8_addon_mrp_operations_start_without_material-8.0.1.0.1.99.dev6.dist-info/RECORD
odoo8_addon_mrp_operations_start_without_material-8.0.1.0.1.99.dev6.dist-info/WHEEL
odoo8_addon_mrp_operations_start_without_material-8.0.1.0.1.99.dev6.dist-info/metadata.json
odoo8_addon_mrp_operations_start_without_material-8.0.1.0.1.99.dev6.dist-info/namespace_packages.txt
odoo8_addon_mrp_operations_start_without_material-8.0.1.0.1.99.dev6.dist-info/top_level.txt
odoo_addons/mrp_operations_start_without_material/README.rst
odoo_addons/mrp_operations_start_without_material/__init__.py
odoo_addons/mrp_operations_start_without_material/__openerp__.py
odoo_addons/mrp_operations_start_without_material/i18n/cs.po
odoo_addons/mrp_operations_start_without_material/i18n/de.po
odoo_addons/mrp_operations_start_without_material/i18n/en_US.po
odoo_addons/mrp_operations_start_without_material/i18n/es.po
odoo_addons/mrp_operations_start_without_material/i18n/fr.po
odoo_addons/mrp_operations_start_without_material/i18n/gl.po
odoo_addons/mrp_operations_start_without_material/i18n/hr.po
odoo_addons/mrp_operations_start_without_material/i18n/it.po
odoo_addons/mrp_operations_start_without_material/i18n/mrp_operations_start_without_material.pot
odoo_addons/mrp_operations_start_without_material/i18n/pt_BR.po
odoo_addons/mrp_operations_start_without_material/i18n/ro.po
odoo_addons/mrp_operations_start_without_material/i18n/sl.po
odoo_addons/mrp_operations_start_without_material/i18n/tr.po
odoo_addons/mrp_operations_start_without_material/i18n/vi_VN.po
odoo_addons/mrp_operations_start_without_material/i18n/zh_CN.po
odoo_addons/mrp_operations_start_without_material/models/__init__.py
odoo_addons/mrp_operations_start_without_material/models/mrp_bom.py
odoo_addons/mrp_operations_start_without_material/models/mrp_production.py
odoo_addons/mrp_operations_start_without_material/models/mrp_routing.py
odoo_addons/mrp_operations_start_without_material/static/description/icon.png
odoo_addons/mrp_operations_start_without_material/tests/__init__.py
odoo_addons/mrp_operations_start_without_material/tests/test_mrp_operation.py
odoo_addons/mrp_operations_start_without_material/views/mrp_production_view.xml
odoo_addons/mrp_operations_start_without_material/views/mrp_routing_view.xml
