Metadata-Version: 2.0
Name: odoo8-addon-mrp-operations-start-without-material
Version: 8.0.1.0.1.99.dev6
Summary: MRP Operations start without material
Home-page: http://www.odoomrp.com
Author: Tecnativa,AvanzOSC,OdooMRP Team,Odoo Community Association (OCA)
Author-email: support@odoo-community.org
License: UNKNOWN
Platform: UNKNOWN
Classifier: Programming Language :: Python
Classifier: Framework :: Odoo
Requires-Python: ~=2.7
Requires-Dist: odoo (<9.0a,>=8.0a)
Requires-Dist: odoo8-addon-mrp-operations-extension
